gitpkg/__init__.py
gitpkg/__main__.py
gitpkg/_version.py
gitpkg/cli/__init__.py
gitpkg/cli/add.py
gitpkg/cli/console.py
gitpkg/cli/dest.py
gitpkg/cli/helpers.py
gitpkg/cli/install.py
gitpkg/cli/list.py
gitpkg/cli/remove.py
gitpkg/cli/root.py
gitpkg/cli/update.py
gitpkg/cli/version.py
gitpkg/config.py
gitpkg/errors.py
gitpkg/main.py
gitpkg/pkg_manager.py
gitpkg/utils.py
gitpkg-0.3.2.dist-info/LICENSE
gitpkg-0.3.2.dist-info/METADATA
gitpkg-0.3.2.dist-info/WHEEL
gitpkg-0.3.2.dist-info/entry_points.txt
gitpkg-0.3.2.dist-info/RECORD
