Metadata-Version: 2.3
Name: gitpkg
Version: 0.3.2
Summary: A git powered package manager built on top of submodules.
License: GPLv3
Keywords: packaging,dependency
Author: Christopher Kaster
Author-email: me@atomicptr.de
Requires-Python: >=3.10,<4
Classifier: License :: OSI Approved :: GNU General Public License v3 (GPLv3)
Classifier: License :: Other/Proprietary License
Classifier: Programming Language :: Python :: 3
Classifier: Programming Language :: Python :: 3.10
Classifier: Programming Language :: Python :: 3.11
Classifier: Programming Language :: Python :: 3.12
Classifier: Programming Language :: Python :: 3.13
Classifier: Topic :: Software Development
Requires-Dist: dataclass-binder (>=0.3.4,<0.4.0)
Requires-Dist: exceptiongroup (>=1,<2) ; python_version < "3.11"
Requires-Dist: gitpython (>=3.1.40,<4.0.0)
Requires-Dist: rich-click (>=1.7.1,<2.0.0)
Requires-Dist: tomli (>=2,<3) ; python_version < "3.11"
Project-URL: Homepage, https://github.com/atomicptr/gitpkg
Project-URL: Repository, https://github.com/atomicptr/gitpkg
